{
  "id": "Eurolite LED Laser Derby",
  "brand": "Eurolite",
  "model": "LED Laser Derby",
  "defaultPersonality": "13-channel mode",
  "personalities": [
    {
      "name": "13-channel mode",
      "channelCount": 13,
      "channels": [
        {
          "offset": 0,
          "name": "Red",
          "type": "red",
          "minValue": 0,
          "maxValue": 255,
          "defaultValue": 0
        },
        {
          "offset": 1,
          "name": "Green",
          "type": "green",
          "minValue": 0,
          "maxValue": 255,
          "defaultValue": 0
        },
        {
          "offset": 2,
          "name": "Blue",
          "type": "blue",
          "minValue": 0,
          "maxValue": 255,
          "defaultValue": 0
        },
        {
          "offset": 3,
          "name": "CoolWhite",
          "type": "other",
          "minValue": 0,
          "maxValue": 255,
          "defaultValue": 0
        },
        {
          "offset": 4,
          "name": "Strobe",
          "type": "strobe",
          "minValue": 0,
          "maxValue": 255,
          "defaultValue": 0
        },
        {
          "offset": 5,
          "name": "Dimmer",
          "type": "dimmer",
          "minValue": 0,
          "maxValue": 255,
          "defaultValue": 0
        },
        {
          "offset": 6,
          "name": "Laser",
          "type": "other",
          "minValue": 0,
          "maxValue": 255,
          "defaultValue": 0
        },
        {
          "offset": 7,
          "name": "Laser Strobe",
          "type": "strobe",
          "minValue": 0,
          "maxValue": 255,
          "defaultValue": 0
        },
        {
          "offset": 8,
          "name": "LED Beams Rotation",
          "type": "other",
          "minValue": 0,
          "maxValue": 255,
          "defaultValue": 0
        },
        {
          "offset": 9,
          "name": "Laser Beams Rotation",
          "type": "other",
          "minValue": 0,
          "maxValue": 255,
          "defaultValue": 0
        },
        {
          "offset": 10,
          "name": "Show Program",
          "type": "other",
          "minValue": 0,
          "maxValue": 255,
          "defaultValue": 0
        },
        {
          "offset": 11,
          "name": "Show Program Speed",
          "type": "speed",
          "minValue": 0,
          "maxValue": 255,
          "defaultValue": 0
        },
        {
          "offset": 12,
          "name": "Auto Mode Show Program",
          "type": "other",
          "minValue": 0,
          "maxValue": 255,
          "defaultValue": 0
        }
      ]
    }
  ]
}
