{
  "id": "Stairville Follow Spot 1200 Pro",
  "brand": "Stairville",
  "model": "Follow Spot 1200 Pro",
  "defaultPersonality": "6-channel mode",
  "personalities": [
    {
      "name": "6-channel mode",
      "channelCount": 6,
      "channels": [
        {
          "offset": 0,
          "name": "Strobe",
          "type": "strobe",
          "minValue": 0,
          "maxValue": 255,
          "defaultValue": 0
        },
        {
          "offset": 1,
          "name": "Iris",
          "type": "iris",
          "minValue": 0,
          "maxValue": 255,
          "defaultValue": 0
        },
        {
          "offset": 2,
          "name": "Color Wheel",
          "type": "color-wheel",
          "minValue": 0,
          "maxValue": 255,
          "defaultValue": 0
        },
        {
          "offset": 3,
          "name": "ColorFilter",
          "type": "other",
          "minValue": 0,
          "maxValue": 255,
          "defaultValue": 0
        },
        {
          "offset": 4,
          "name": "Dimmer",
          "type": "dimmer",
          "minValue": 0,
          "maxValue": 255,
          "defaultValue": 0
        },
        {
          "offset": 5,
          "name": "Focus",
          "type": "focus",
          "minValue": 0,
          "maxValue": 255,
          "defaultValue": 0
        }
      ]
    }
  ]
}
